netbox_sync/__init__.py
netbox_sync-0.0.0.dist-info/LICENSE.txt
netbox_sync-0.0.0.dist-info/METADATA
netbox_sync-0.0.0.dist-info/WHEEL
netbox_sync-0.0.0.dist-info/top_level.txt
netbox_sync-0.0.0.dist-info/RECORD
