Metadata-Version: 2.1
Name: netbox-sync
Version: 0.0.0
Summary: Netbox Sync
Home-page: https://github.com/dansheps/netbox-sync/
Download-URL: https://www.pypi.org/project/netbox-sync/
Author: Daniel Sheppard
Author-email: dans@dansheps.com
License: Apache 2.0
Platform: UNKNOWN
Classifier: Programming Language :: Python :: 3
Classifier: License :: OSI Approved :: MIT License
Classifier: Operating System :: OS Independent
Requires-Python: >=3.8
License-File: LICENSE.txt
Requires-Dist: importlib
Requires-Dist: napalm
